pytidy/__init__.py
pytidy/decorators.py
pytidy/error.py
pytidy/registry.py
tests/__init__.py
tests/test_dataclass.py
tests/test_function.py
tests/test_registry.py
pytidy-0.4.0.dist-info/LICENSE
pytidy-0.4.0.dist-info/METADATA
pytidy-0.4.0.dist-info/WHEEL
pytidy-0.4.0.dist-info/top_level.txt
pytidy-0.4.0.dist-info/RECORD
