Metadata-Version: 2.1
Name: pytidy
Version: 0.4.0
Summary: Dependency Injection library based on type hints
Home-page: https://github.com/taxpon/pytidy
Author: Takuro Wada
Author-email: taxpon@gmail.com
License: UNKNOWN
Platform: UNKNOWN
Classifier: Programming Language :: Python :: 3
Classifier: License :: OSI Approved :: MIT License
Classifier: Topic :: Software Development :: Libraries :: Application Frameworks
Requires-Python: >=3.6
